{
  "idx_to_code": {
    "0": "2PLANT",
    "1": "2PLANT-S",
    "2": "ABAM",
    "3": "ABBA",
    "4": "ABCO",
    "5": "ABFR",
    "6": "ABIES",
    "7": "ABLAL",
    "8": "ABLO",
    "9": "ABMA",
    "10": "ACBA3",
    "11": "ACCI",
    "12": "ACNE2",
    "13": "ACNEN",
    "14": "ACPE",
    "15": "ACRU",
    "16": "ACRUR",
    "17": "ACSA2",
    "18": "ACSA3",
    "19": "ACSAS",
    "20": "AIAL",
    "21": "ALRU2",
    "22": "AMLA",
    "23": "ARVIM",
    "24": "BEAL2",
    "25": "BECAC",
    "26": "BELE",
    "27": "BENE4",
    "28": "BENI",
    "29": "BEPA",
    "30": "BEPAP",
    "31": "BEPO",
    "32": "BOSU2",
    "33": "BUBU",
    "34": "BUSI",
    "35": "CAAQ2",
    "36": "CACA18",
    "37": "CACO15",
    "38": "CADE12",
    "39": "CADE27",
    "40": "CAGL8",
    "41": "CAIL2",
    "42": "CAOV2",
    "43": "CARYA",
    "44": "CATO6",
    "45": "CECA4",
    "46": "CECAC",
    "47": "CELA",
    "48": "CELTI",
    "49": "CEOC",
    "50": "CODR",
    "51": "COFL2",
    "52": "CONU4",
    "53": "DIVI5",
    "54": "FAGR",
    "55": "FRAM2",
    "56": "FRAXI",
    "57": "FRNI",
    "58": "FRPE",
    "59": "GLTR",
    "60": "GOLA",
    "61": "GYDI",
    "62": "HADI3",
    "63": "HATE3",
    "64": "ILMO",
    "65": "ILOP",
    "66": "JUNI",
    "67": "JUOS",
    "68": "JUVI",
    "69": "LALA",
    "70": "LIST2",
    "71": "LITU",
    "72": "MAAC",
    "73": "MAFR",
    "74": "MAMA2",
    "75": "MAPO",
    "76": "MEAZ",
    "77": "MEPO5",
    "78": "MORU2",
    "79": "NYAQ2",
    "80": "NYBI",
    "81": "NYSY",
    "82": "OSVI",
    "83": "OXAR",
    "84": "PIAB",
    "85": "PIAL3",
    "86": "PICEA",
    "87": "PICO",
    "88": "PICOL",
    "89": "PIEC2",
    "90": "PIED",
    "91": "PIEL",
    "92": "PIEN",
    "93": "PIFL2",
    "94": "PIGL",
    "95": "PIJE",
    "96": "PIMA",
    "97": "PIMO3",
    "98": "PINACE",
    "99": "PINUS",
    "100": "PIPA2",
    "101": "PIPO",
    "102": "PIPOS",
    "103": "PIPU5",
    "104": "PIRE",
    "105": "PIRI",
    "106": "PIRU",
    "107": "PISA2",
    "108": "PIST",
    "109": "PITA",
    "110": "PIVI2",
    "111": "PLOC",
    "112": "PODE3",
    "113": "POGR4",
    "114": "POTR5",
    "115": "PRAM",
    "116": "PRME",
    "117": "PRPEP",
    "118": "PRSE2",
    "119": "PRSES",
    "120": "PSME",
    "121": "PSMEM",
    "122": "QUAL",
    "123": "QUCH2",
    "124": "QUCO2",
    "125": "QUDO",
    "126": "QUERC",
    "127": "QUFA",
    "128": "QUGE2",
    "129": "QUHE2",
    "130": "QUKE",
    "131": "QULA2",
    "132": "QULA3",
    "133": "QULY",
    "134": "QUMA13",
    "135": "QUMA2",
    "136": "QUMA3",
    "137": "QUMI",
    "138": "QUMO4",
    "139": "QUMU",
    "140": "QUNI",
    "141": "QUPA5",
    "142": "QUPH",
    "143": "QURU",
    "144": "QUSH",
    "145": "QUST",
    "146": "QUVE",
    "147": "QUVI",
    "148": "QUWI2",
    "149": "ROMU",
    "150": "ROPS",
    "151": "SAAL5",
    "152": "SANI",
    "153": "SILA20",
    "154": "SYOR",
    "155": "TABR2",
    "156": "THOC2",
    "157": "THPL",
    "158": "TIAM",
    "159": "TRSE6",
    "160": "TSCA",
    "161": "TSHE",
    "162": "ULAL",
    "163": "ULAM",
    "164": "ULCR",
    "165": "ULMUS",
    "166": "ULRU"
  },
  "idx_to_name": {
    "0": "Unknown plant",
    "1": "Unknown softwood plant",
    "2": "Abies amabilis (Douglas ex Loudon) Douglas ex Forbes",
    "3": "Abies balsamea (L.) Mill.",
    "4": "Abies concolor (Gord. & Glend.) Lindl. ex Hildebr.",
    "5": "Abies fraseri (Pursh) Poir.",
    "6": "Abies sp.",
    "7": "Abies lasiocarpa (Hook.) Nutt. var. lasiocarpa",
    "8": "Abies lowiana (Gordon & Glend.) A. Murray bis",
    "9": "Abies magnifica A. Murray bis",
    "10": "Acer barbatum Michx.",
    "11": "Acer circinatum Pursh",
    "12": "Acer negundo L.",
    "13": "Acer negundo L. var. negundo",
    "14": "Acer pensylvanicum L.",
    "15": "Acer rubrum L.",
    "16": "Acer rubrum L. var. rubrum",
    "17": "Acer saccharinum L.",
    "18": "Acer saccharum Marshall",
    "19": "Acer saccharum Marshall var. saccharum",
    "20": "Ailanthus altissima (Mill.) Swingle",
    "21": "Alnus rubra Bong.",
    "22": "Amelanchier laevis Wiegand",
    "23": "Arctostaphylos viscida Parry ssp. mariposa (Dudley) P.V. Wells",
    "24": "Betula alleghaniensis Britton",
    "25": "Betula \u00d7caerulea Blanch. var. caerulea",
    "26": "Betula lenta L.",
    "27": "Betula neoalaskana Sarg.",
    "28": "Betula nigra L.",
    "29": "Betula papyrifera Marshall",
    "30": "Betula papyrifera Marshall var. papyrifera",
    "31": "Betula populifolia Marshall",
    "32": "Bourreria succulenta Jacq.",
    "33": "Bucida buceras L.",
    "34": "Bursera simaruba (L.) Sarg.",
    "35": "Carya aquatica (Michx. f.) Nutt.",
    "36": "Carpinus caroliniana Walter",
    "37": "Carya cordiformis (Wangenh.) K. Koch",
    "38": "Castanea dentata (Marshall) Borkh.",
    "39": "Calocedrus decurrens (Torr.) Florin",
    "40": "Carya glabra (Mill.) Sweet",
    "41": "Carya illinoinensis (Wangenh.) K. Koch",
    "42": "Carya ovata (Mill.) K. Koch",
    "43": "Carya sp.",
    "44": "Carya tomentosa (Lam.) Nutt.",
    "45": "Cercis canadensis L.",
    "46": "Cercis canadensis L. var. canadensis",
    "47": "Celtis laevigata Willd.",
    "48": "Celtis sp.",
    "49": "Celtis occidentalis L.",
    "50": "Cornus drummondii C.A. Mey.",
    "51": "Cornus florida L.",
    "52": "Cornus nuttallii Audubon ex Torr. & A. Gray",
    "53": "Diospyros virginiana L.",
    "54": "Fagus grandifolia Ehrh.",
    "55": "Fraxinus americana L.",
    "56": "Fraxinus sp.",
    "57": "Fraxinus nigra Marshall",
    "58": "Fraxinus pennsylvanica Marshall",
    "59": "Gleditsia triacanthos L.",
    "60": "Gordonia lasianthus (L.) Ellis",
    "61": "Gymnocladus dioicus (L.) K. Koch",
    "62": "Halesia diptera Ellis",
    "63": "Halesia tetraptera Ellis",
    "64": "Ilex montana Torr. & A. Gray ex A. Gray",
    "65": "Ilex opaca Aiton",
    "66": "Juglans nigra L.",
    "67": "Juniperus osteosperma (Torr.) Little",
    "68": "Juniperus virginiana L.",
    "69": "Larix laricina (Du Roi) K. Koch",
    "70": "Liquidambar styraciflua L.",
    "71": "Liriodendron tulipifera L.",
    "72": "Magnolia acuminata (L.) L.",
    "73": "Magnolia fraseri Walter",
    "74": "Magnolia macrophylla Michx.",
    "75": "Maclura pomifera (Raf.) C.K. Schneid.",
    "76": "Melia azedarach L.",
    "77": "Metrosideros polymorpha Gaudich.",
    "78": "Morus rubra L.",
    "79": "Nyssa aquatica L.",
    "80": "Nyssa biflora Walter",
    "81": "Nyssa sylvatica Marshall",
    "82": "Ostrya virginiana (Mill.) K. Koch",
    "83": "Oxydendrum arboreum (L.) DC.",
    "84": "Picea abies (L.) Karst.",
    "85": "Pisonia albida (Heimerl) Britton ex Standl.",
    "86": "Picea sp.",
    "87": "Pinus contorta Douglas ex Loudon",
    "88": "Pinus contorta Douglas ex Loudon var. latifolia Engelm. ex S. Watson",
    "89": "Pinus echinata Mill.",
    "90": "Pinus edulis Engelm.",
    "91": "Pinus elliottii Engelm.",
    "92": "Picea engelmannii Parry ex Engelm.",
    "93": "Pinus flexilis James",
    "94": "Picea glauca (Moench) Voss",
    "95": "Pinus jeffreyi Balf.",
    "96": "Picea mariana (Mill.) Britton, Sterns & Poggenb.",
    "97": "Pinus monticola Douglas ex D. Don",
    "98": "Pinaceae sp.",
    "99": "Pinus sp.",
    "100": "Pinus palustris Mill.",
    "101": "Pinus ponderosa Lawson & C. Lawson",
    "102": "Pinus ponderosa Lawson & C. Lawson var. scopulorum Engelm.",
    "103": "Pinus pungens Lamb.",
    "104": "Pinus resinosa Aiton",
    "105": "Pinus rigida Mill.",
    "106": "Picea rubens Sarg.",
    "107": "Pinus sabiniana Douglas ex Douglas",
    "108": "Pinus strobus L.",
    "109": "Pinus taeda L.",
    "110": "Pinus virginiana Mill.",
    "111": "Platanus occidentalis L.",
    "112": "Populus deltoides W. Bartram ex Marshall",
    "113": "Populus grandidentata Michx.",
    "114": "Populus tremuloides Michx.",
    "115": "Prunus americana Marshall",
    "116": "Prunus mexicana S. Watson",
    "117": "Prunus pensylvanica L. f. var. pensylvanica",
    "118": "Prunus serotina Ehrh.",
    "119": "Prunus serotina Ehrh. var. serotina",
    "120": "Pseudotsuga menziesii (Mirb.) Franco",
    "121": "Pseudotsuga menziesii (Mirb.) Franco var. menziesii",
    "122": "Quercus alba L.",
    "123": "Quercus chrysolepis Liebm.",
    "124": "Quercus coccinea M\u00fcnchh.",
    "125": "Quercus douglasii Hook. & Arn.",
    "126": "Quercus sp.",
    "127": "Quercus falcata Michx.",
    "128": "Quercus geminata Small",
    "129": "Quercus hemisphaerica W. Bartram ex Willd.",
    "130": "Quercus kelloggii Newberry",
    "131": "Quercus laevis Walter",
    "132": "Quercus laurifolia Michx.",
    "133": "Quercus lyrata Walter",
    "134": "Quercus margaretta",
    "135": "Quercus macrocarpa Michx.",
    "136": "Quercus marilandica M\u00fcnchh.",
    "137": "Quercus michauxii Nutt.",
    "138": "Quercus montana Willd.",
    "139": "Quercus muehlenbergii Engelm.",
    "140": "Quercus nigra L.",
    "141": "Quercus pagoda Raf.",
    "142": "Quercus phellos L.",
    "143": "Quercus rubra L.",
    "144": "Quercus shumardii Buckley",
    "145": "Quercus stellata Wangenh.",
    "146": "Quercus velutina Lam.",
    "147": "Quercus virginiana Mill.",
    "148": "Quercus wislizeni A. DC.",
    "149": "Rosa multiflora Thunb.",
    "150": "Robinia pseudoacacia L.",
    "151": "Sassafras albidum (Nutt.) Nees",
    "152": "Salix nigra Marshall",
    "153": "Sideroxylon lanuginosum Michx.",
    "154": "Symphoricarpos orbiculatus Moench",
    "155": "Taxus brevifolia Nutt.",
    "156": "Thuja occidentalis L.",
    "157": "Thuja plicata Donn ex D. Don",
    "158": "Tilia americana L.",
    "159": "Triadica sebifera (L.) Small",
    "160": "Tsuga canadensis (L.) Carri\u00e8re",
    "161": "Tsuga heterophylla (Raf.) Sarg.",
    "162": "Ulmus alata Michx.",
    "163": "Ulmus americana L.",
    "164": "Ulmus crassifolia Nutt.",
    "165": "Ulmus sp.",
    "166": "Ulmus rubra Muhl."
  },
  "code_to_idx": {
    "2PLANT": 0,
    "2PLANT-S": 1,
    "ABAM": 2,
    "ABBA": 3,
    "ABCO": 4,
    "ABFR": 5,
    "ABIES": 6,
    "ABLAL": 7,
    "ABLO": 8,
    "ABMA": 9,
    "ACBA3": 10,
    "ACCI": 11,
    "ACNE2": 12,
    "ACNEN": 13,
    "ACPE": 14,
    "ACRU": 15,
    "ACRUR": 16,
    "ACSA2": 17,
    "ACSA3": 18,
    "ACSAS": 19,
    "AIAL": 20,
    "ALRU2": 21,
    "AMLA": 22,
    "ARVIM": 23,
    "BEAL2": 24,
    "BECAC": 25,
    "BELE": 26,
    "BENE4": 27,
    "BENI": 28,
    "BEPA": 29,
    "BEPAP": 30,
    "BEPO": 31,
    "BOSU2": 32,
    "BUBU": 33,
    "BUSI": 34,
    "CAAQ2": 35,
    "CACA18": 36,
    "CACO15": 37,
    "CADE12": 38,
    "CADE27": 39,
    "CAGL8": 40,
    "CAIL2": 41,
    "CAOV2": 42,
    "CARYA": 43,
    "CATO6": 44,
    "CECA4": 45,
    "CECAC": 46,
    "CELA": 47,
    "CELTI": 48,
    "CEOC": 49,
    "CODR": 50,
    "COFL2": 51,
    "CONU4": 52,
    "DIVI5": 53,
    "FAGR": 54,
    "FRAM2": 55,
    "FRAXI": 56,
    "FRNI": 57,
    "FRPE": 58,
    "GLTR": 59,
    "GOLA": 60,
    "GYDI": 61,
    "HADI3": 62,
    "HATE3": 63,
    "ILMO": 64,
    "ILOP": 65,
    "JUNI": 66,
    "JUOS": 67,
    "JUVI": 68,
    "LALA": 69,
    "LIST2": 70,
    "LITU": 71,
    "MAAC": 72,
    "MAFR": 73,
    "MAMA2": 74,
    "MAPO": 75,
    "MEAZ": 76,
    "MEPO5": 77,
    "MORU2": 78,
    "NYAQ2": 79,
    "NYBI": 80,
    "NYSY": 81,
    "OSVI": 82,
    "OXAR": 83,
    "PIAB": 84,
    "PIAL3": 85,
    "PICEA": 86,
    "PICO": 87,
    "PICOL": 88,
    "PIEC2": 89,
    "PIED": 90,
    "PIEL": 91,
    "PIEN": 92,
    "PIFL2": 93,
    "PIGL": 94,
    "PIJE": 95,
    "PIMA": 96,
    "PIMO3": 97,
    "PINACE": 98,
    "PINUS": 99,
    "PIPA2": 100,
    "PIPO": 101,
    "PIPOS": 102,
    "PIPU5": 103,
    "PIRE": 104,
    "PIRI": 105,
    "PIRU": 106,
    "PISA2": 107,
    "PIST": 108,
    "PITA": 109,
    "PIVI2": 110,
    "PLOC": 111,
    "PODE3": 112,
    "POGR4": 113,
    "POTR5": 114,
    "PRAM": 115,
    "PRME": 116,
    "PRPEP": 117,
    "PRSE2": 118,
    "PRSES": 119,
    "PSME": 120,
    "PSMEM": 121,
    "QUAL": 122,
    "QUCH2": 123,
    "QUCO2": 124,
    "QUDO": 125,
    "QUERC": 126,
    "QUFA": 127,
    "QUGE2": 128,
    "QUHE2": 129,
    "QUKE": 130,
    "QULA2": 131,
    "QULA3": 132,
    "QULY": 133,
    "QUMA13": 134,
    "QUMA2": 135,
    "QUMA3": 136,
    "QUMI": 137,
    "QUMO4": 138,
    "QUMU": 139,
    "QUNI": 140,
    "QUPA5": 141,
    "QUPH": 142,
    "QURU": 143,
    "QUSH": 144,
    "QUST": 145,
    "QUVE": 146,
    "QUVI": 147,
    "QUWI2": 148,
    "ROMU": 149,
    "ROPS": 150,
    "SAAL5": 151,
    "SANI": 152,
    "SILA20": 153,
    "SYOR": 154,
    "TABR2": 155,
    "THOC2": 156,
    "THPL": 157,
    "TIAM": 158,
    "TRSE6": 159,
    "TSCA": 160,
    "TSHE": 161,
    "ULAL": 162,
    "ULAM": 163,
    "ULCR": 164,
    "ULMUS": 165,
    "ULRU": 166
  },
  "name_to_idx": {
    "Unknown plant": 0,
    "Unknown softwood plant": 1,
    "Abies amabilis (Douglas ex Loudon) Douglas ex Forbes": 2,
    "Abies balsamea (L.) Mill.": 3,
    "Abies concolor (Gord. & Glend.) Lindl. ex Hildebr.": 4,
    "Abies fraseri (Pursh) Poir.": 5,
    "Abies sp.": 6,
    "Abies lasiocarpa (Hook.) Nutt. var. lasiocarpa": 7,
    "Abies lowiana (Gordon & Glend.) A. Murray bis": 8,
    "Abies magnifica A. Murray bis": 9,
    "Acer barbatum Michx.": 10,
    "Acer circinatum Pursh": 11,
    "Acer negundo L.": 12,
    "Acer negundo L. var. negundo": 13,
    "Acer pensylvanicum L.": 14,
    "Acer rubrum L.": 15,
    "Acer rubrum L. var. rubrum": 16,
    "Acer saccharinum L.": 17,
    "Acer saccharum Marshall": 18,
    "Acer saccharum Marshall var. saccharum": 19,
    "Ailanthus altissima (Mill.) Swingle": 20,
    "Alnus rubra Bong.": 21,
    "Amelanchier laevis Wiegand": 22,
    "Arctostaphylos viscida Parry ssp. mariposa (Dudley) P.V. Wells": 23,
    "Betula alleghaniensis Britton": 24,
    "Betula \u00d7caerulea Blanch. var. caerulea": 25,
    "Betula lenta L.": 26,
    "Betula neoalaskana Sarg.": 27,
    "Betula nigra L.": 28,
    "Betula papyrifera Marshall": 29,
    "Betula papyrifera Marshall var. papyrifera": 30,
    "Betula populifolia Marshall": 31,
    "Bourreria succulenta Jacq.": 32,
    "Bucida buceras L.": 33,
    "Bursera simaruba (L.) Sarg.": 34,
    "Carya aquatica (Michx. f.) Nutt.": 35,
    "Carpinus caroliniana Walter": 36,
    "Carya cordiformis (Wangenh.) K. Koch": 37,
    "Castanea dentata (Marshall) Borkh.": 38,
    "Calocedrus decurrens (Torr.) Florin": 39,
    "Carya glabra (Mill.) Sweet": 40,
    "Carya illinoinensis (Wangenh.) K. Koch": 41,
    "Carya ovata (Mill.) K. Koch": 42,
    "Carya sp.": 43,
    "Carya tomentosa (Lam.) Nutt.": 44,
    "Cercis canadensis L.": 45,
    "Cercis canadensis L. var. canadensis": 46,
    "Celtis laevigata Willd.": 47,
    "Celtis sp.": 48,
    "Celtis occidentalis L.": 49,
    "Cornus drummondii C.A. Mey.": 50,
    "Cornus florida L.": 51,
    "Cornus nuttallii Audubon ex Torr. & A. Gray": 52,
    "Diospyros virginiana L.": 53,
    "Fagus grandifolia Ehrh.": 54,
    "Fraxinus americana L.": 55,
    "Fraxinus sp.": 56,
    "Fraxinus nigra Marshall": 57,
    "Fraxinus pennsylvanica Marshall": 58,
    "Gleditsia triacanthos L.": 59,
    "Gordonia lasianthus (L.) Ellis": 60,
    "Gymnocladus dioicus (L.) K. Koch": 61,
    "Halesia diptera Ellis": 62,
    "Halesia tetraptera Ellis": 63,
    "Ilex montana Torr. & A. Gray ex A. Gray": 64,
    "Ilex opaca Aiton": 65,
    "Juglans nigra L.": 66,
    "Juniperus osteosperma (Torr.) Little": 67,
    "Juniperus virginiana L.": 68,
    "Larix laricina (Du Roi) K. Koch": 69,
    "Liquidambar styraciflua L.": 70,
    "Liriodendron tulipifera L.": 71,
    "Magnolia acuminata (L.) L.": 72,
    "Magnolia fraseri Walter": 73,
    "Magnolia macrophylla Michx.": 74,
    "Maclura pomifera (Raf.) C.K. Schneid.": 75,
    "Melia azedarach L.": 76,
    "Metrosideros polymorpha Gaudich.": 77,
    "Morus rubra L.": 78,
    "Nyssa aquatica L.": 79,
    "Nyssa biflora Walter": 80,
    "Nyssa sylvatica Marshall": 81,
    "Ostrya virginiana (Mill.) K. Koch": 82,
    "Oxydendrum arboreum (L.) DC.": 83,
    "Picea abies (L.) Karst.": 84,
    "Pisonia albida (Heimerl) Britton ex Standl.": 85,
    "Picea sp.": 86,
    "Pinus contorta Douglas ex Loudon": 87,
    "Pinus contorta Douglas ex Loudon var. latifolia Engelm. ex S. Watson": 88,
    "Pinus echinata Mill.": 89,
    "Pinus edulis Engelm.": 90,
    "Pinus elliottii Engelm.": 91,
    "Picea engelmannii Parry ex Engelm.": 92,
    "Pinus flexilis James": 93,
    "Picea glauca (Moench) Voss": 94,
    "Pinus jeffreyi Balf.": 95,
    "Picea mariana (Mill.) Britton, Sterns & Poggenb.": 96,
    "Pinus monticola Douglas ex D. Don": 97,
    "Pinaceae sp.": 98,
    "Pinus sp.": 99,
    "Pinus palustris Mill.": 100,
    "Pinus ponderosa Lawson & C. Lawson": 101,
    "Pinus ponderosa Lawson & C. Lawson var. scopulorum Engelm.": 102,
    "Pinus pungens Lamb.": 103,
    "Pinus resinosa Aiton": 104,
    "Pinus rigida Mill.": 105,
    "Picea rubens Sarg.": 106,
    "Pinus sabiniana Douglas ex Douglas": 107,
    "Pinus strobus L.": 108,
    "Pinus taeda L.": 109,
    "Pinus virginiana Mill.": 110,
    "Platanus occidentalis L.": 111,
    "Populus deltoides W. Bartram ex Marshall": 112,
    "Populus grandidentata Michx.": 113,
    "Populus tremuloides Michx.": 114,
    "Prunus americana Marshall": 115,
    "Prunus mexicana S. Watson": 116,
    "Prunus pensylvanica L. f. var. pensylvanica": 117,
    "Prunus serotina Ehrh.": 118,
    "Prunus serotina Ehrh. var. serotina": 119,
    "Pseudotsuga menziesii (Mirb.) Franco": 120,
    "Pseudotsuga menziesii (Mirb.) Franco var. menziesii": 121,
    "Quercus alba L.": 122,
    "Quercus chrysolepis Liebm.": 123,
    "Quercus coccinea M\u00fcnchh.": 124,
    "Quercus douglasii Hook. & Arn.": 125,
    "Quercus sp.": 126,
    "Quercus falcata Michx.": 127,
    "Quercus geminata Small": 128,
    "Quercus hemisphaerica W. Bartram ex Willd.": 129,
    "Quercus kelloggii Newberry": 130,
    "Quercus laevis Walter": 131,
    "Quercus laurifolia Michx.": 132,
    "Quercus lyrata Walter": 133,
    "Quercus margaretta": 134,
    "Quercus macrocarpa Michx.": 135,
    "Quercus marilandica M\u00fcnchh.": 136,
    "Quercus michauxii Nutt.": 137,
    "Quercus montana Willd.": 138,
    "Quercus muehlenbergii Engelm.": 139,
    "Quercus nigra L.": 140,
    "Quercus pagoda Raf.": 141,
    "Quercus phellos L.": 142,
    "Quercus rubra L.": 143,
    "Quercus shumardii Buckley": 144,
    "Quercus stellata Wangenh.": 145,
    "Quercus velutina Lam.": 146,
    "Quercus virginiana Mill.": 147,
    "Quercus wislizeni A. DC.": 148,
    "Rosa multiflora Thunb.": 149,
    "Robinia pseudoacacia L.": 150,
    "Sassafras albidum (Nutt.) Nees": 151,
    "Salix nigra Marshall": 152,
    "Sideroxylon lanuginosum Michx.": 153,
    "Symphoricarpos orbiculatus Moench": 154,
    "Taxus brevifolia Nutt.": 155,
    "Thuja occidentalis L.": 156,
    "Thuja plicata Donn ex D. Don": 157,
    "Tilia americana L.": 158,
    "Triadica sebifera (L.) Small": 159,
    "Tsuga canadensis (L.) Carri\u00e8re": 160,
    "Tsuga heterophylla (Raf.) Sarg.": 161,
    "Ulmus alata Michx.": 162,
    "Ulmus americana L.": 163,
    "Ulmus crassifolia Nutt.": 164,
    "Ulmus sp.": 165,
    "Ulmus rubra Muhl.": 166
  },
  "idx_to_count": {
    "0": 135,
    "1": 12,
    "2": 422,
    "3": 260,
    "4": 21,
    "5": 6,
    "6": 19,
    "7": 649,
    "8": 148,
    "9": 126,
    "10": 22,
    "11": 28,
    "12": 215,
    "13": 12,
    "14": 90,
    "15": 5684,
    "16": 23,
    "17": 34,
    "18": 388,
    "19": 139,
    "20": 8,
    "21": 60,
    "22": 545,
    "23": 7,
    "24": 467,
    "25": 7,
    "26": 469,
    "27": 472,
    "28": 6,
    "29": 68,
    "30": 292,
    "31": 13,
    "32": 45,
    "33": 34,
    "34": 17,
    "35": 21,
    "36": 566,
    "37": 16,
    "38": 11,
    "39": 184,
    "40": 92,
    "41": 35,
    "42": 268,
    "43": 15,
    "44": 566,
    "45": 57,
    "46": 24,
    "47": 892,
    "48": 10,
    "49": 143,
    "50": 9,
    "51": 99,
    "52": 6,
    "53": 46,
    "54": 860,
    "55": 173,
    "56": 108,
    "57": 123,
    "58": 553,
    "59": 39,
    "60": 6,
    "61": 9,
    "62": 17,
    "63": 102,
    "64": 15,
    "65": 24,
    "66": 106,
    "67": 12,
    "68": 289,
    "69": 38,
    "70": 942,
    "71": 1152,
    "72": 129,
    "73": 58,
    "74": 8,
    "75": 56,
    "76": 21,
    "77": 55,
    "78": 185,
    "79": 40,
    "80": 64,
    "81": 573,
    "82": 30,
    "83": 331,
    "84": 241,
    "85": 24,
    "86": 8,
    "87": 153,
    "88": 2011,
    "89": 120,
    "90": 6,
    "91": 43,
    "92": 635,
    "93": 173,
    "94": 327,
    "95": 49,
    "96": 1047,
    "97": 36,
    "98": 26,
    "99": 60,
    "100": 2207,
    "101": 91,
    "102": 241,
    "103": 34,
    "104": 577,
    "105": 46,
    "106": 340,
    "107": 9,
    "108": 480,
    "109": 248,
    "110": 16,
    "111": 133,
    "112": 16,
    "113": 149,
    "114": 1362,
    "115": 20,
    "116": 22,
    "117": 13,
    "118": 90,
    "119": 77,
    "120": 333,
    "121": 2978,
    "122": 1139,
    "123": 59,
    "124": 457,
    "125": 15,
    "126": 131,
    "127": 70,
    "128": 50,
    "129": 198,
    "130": 43,
    "131": 566,
    "132": 44,
    "133": 103,
    "134": 228,
    "135": 10,
    "136": 208,
    "137": 87,
    "138": 417,
    "139": 50,
    "140": 272,
    "141": 96,
    "142": 18,
    "143": 2086,
    "144": 20,
    "145": 958,
    "146": 110,
    "147": 13,
    "148": 31,
    "149": 14,
    "150": 114,
    "151": 82,
    "152": 6,
    "153": 12,
    "154": 45,
    "155": 86,
    "156": 11,
    "157": 121,
    "158": 45,
    "159": 49,
    "160": 3303,
    "161": 1425,
    "162": 74,
    "163": 300,
    "164": 109,
    "165": 56,
    "166": 78
  },
  "metadata": {
    "taxonomic_level": "species",
    "num_classes": 167,
    "total_samples": 47971,
    "source_csv": "combined_dataset.csv",
    "description": "NEON tree species classification - Species level (USDA plant codes)",
    "label_format": "USDA plant symbol codes (e.g., PSMEM for Pseudotsuga menziesii)"
  }
}